pyparliment/__init__.py
pyparliment/business.py
pyparliment/commons.py
pyparliment/lords.py
pyparliment/now.py
pyparliment/treaties.py
pyparliment/may/__init__.py
pyparliment/may/navigation.py
pyparliment/may/search.py
pyparliment/members/__init__.py
pyparliment/members/intrests.py
pyparliment/members/parties.py
pyparliment/members/posts.py
pyparliment/members/reference.py
pyparliment/members/location/__init__.py
pyparliment/members/location/constituincy.py
pyparliment/members/location/elections.py
pyparliment/members/location/find.py
pyparliment/members/members/__init__.py
pyparliment/members/members/find.py
pyparliment/members/members/member.py
pyparliment/questions/__init__.py
pyparliment/questions/oral.py
pyparliment/questions/written/__init__.py
pyparliment/questions/written/questions.py
pyparliment/questions/written/reports.py
pyparliment/questions/written/statements.py
pyparliment/statutory/__init__.py
pyparliment/statutory/instruments.py
pyparliment/statutory/procedure.py
PyParliment-0.0.3.dist-info/AUTHORS.rst
PyParliment-0.0.3.dist-info/LICENSE.txt
PyParliment-0.0.3.dist-info/METADATA
PyParliment-0.0.3.dist-info/WHEEL
PyParliment-0.0.3.dist-info/top_level.txt
PyParliment-0.0.3.dist-info/RECORD
