Metadata-Version: 2.1
Name: PyParliment
Version: 0.0.3
Summary: A python library to interact with the UK Houses Of Parliment API
Home-page: https://github.com/Reclaim-The-Night-Leeds/
Author: Reclaim The Night Leeds
Author-email: RTNLeeds@gmail.com
License: MIT
Project-URL: Source, https://github.com/Reclaim-The-Night-Leeds/PyParliment
Project-URL: Changelog, https://github.com/Reclaim-The-Night-Leeds/PyParliment/blob/main/CHANGELOG.rst
Project-URL: Twitter, https://twitter.com/RTN_Leeds
Platform: any
Classifier: Development Status :: 4 - Beta
Classifier: Programming Language :: Python
License-File: LICENSE.txt
License-File: AUTHORS.rst
Requires-Dist: requests
Requires-Dist: pandas
Requires-Dist: shapely
Requires-Dist: importlib-metadata ; python_version < "3.8"
Provides-Extra: testing
Requires-Dist: setuptools ; extra == 'testing'
Requires-Dist: pytest ; extra == 'testing'
Requires-Dist: pytest-cov ; extra == 'testing'
